makemahjongg/__init__.py
makemahjongg/__main__.py
makemahjongg/blank.png
makemahjongg/blank_selected.png
makemahjongg/tileset_blank.png
makemahjongg/tileutil.py
makemahjongg-0.1.0.dist-info/METADATA
makemahjongg-0.1.0.dist-info/WHEEL
makemahjongg-0.1.0.dist-info/entry_points.txt
makemahjongg-0.1.0.dist-info/top_level.txt
makemahjongg-0.1.0.dist-info/RECORD
