Metadata-Version: 2.1
Name: makemahjongg
Version: 0.1.0
Summary: Tileset creator for GNOME Mahjongg
Author-email: Jonas Santoso <santojo@pm.me>
Project-URL: Homepage, https://github.com/santosoj/makemahjongg
Requires-Python: >=3.10
Requires-Dist: Pillow ==9.5.0
